{
  "page": 1,
  "results": [
    {
      "adult": false,
      "gender": 0,
      "id": 3015940,
      "known_for_department": "Acting",
      "name": "Kelli",
      "original_name": "Kelli",
      "popularity": 0.6,
      "profile_path": null,
      "known_for": [
        {
          "adult": false,
          "backdrop_path": null,
          "id": 807530,
          "title": "Hot Body Competition: Beverly Hills Naked Covergirl Model Contest",
          "original_language": "en",
          "original_title": "Hot Body Competition: Beverly Hills Naked Covergirl Model Contest",
          "overview": "Join John Cross and the Hot Body gang as they do it again at Deja Vu Showgirls in North Hollywood. The Beverly Hills Covergirl  Model Contest turns into an all nude affair offering unbelievable new talent, as beautiful \"Covergirls\" display their centerfold quality talents. Watch as 14 exhibitionists show off everything they can and enjoy 8 soothing private dances from Alex, Kandi Kane, Peggy, Michelle, Gina, Shelly Jones, Cleo and Sofia.  Go backstage for more revealing action than you can dream. Go online and match your picks with the judges. It's a front row seat to a very amazing contest.",
          "poster_path": "/M8ZhdfNICDjEZElWbQxeWavfM5.jpg",
          "media_type": "movie",
          "genre_ids": [
            99
          ],
          "popularity": 1.021,
          "release_date": "2005-05-17",
          "video": true,
          "vote_average": 6.5,
          "vote_count": 2
        }
      ]
    },
    {
      "adult": false,
      "gender": 1,
      "id": 95468,
      "known_for_department": "Acting",
      "name": "Kelli Williams",
      "original_name": "Kelli Williams",
      "popularity": 16.216,
      "profile_path": "/6P8MzCm2rgBJFVciaka2r6E6TIt.jpg",
      "known_for": [
        {
          "adult": false,
          "backdrop_path": "/1GY7ih45OzZKjNCJ97XHxBCtuSU.jpg",
          "id": 8358,
          "name": "Lie to Me",
          "original_language": "en",
          "original_name": "Lie to Me",
          "overview": "The world's leading deception researcher, Dr. Cal Lightman, studies facial expression, body language and tone of voice to determine when a person is lying and why, which helps law enforcement and government agencies uncover the truth. But his skills also make it easier for him to deceive others.",
          "poster_path": "/rrTeGVXHqppoTUydoWV6bCzZs1W.jpg",
          "media_type": "tv",
          "genre_ids": [
            80,
            18,
            9648
          ],
          "popularity": 415.996,
          "first_air_date": "2009-01-21",
          "vote_average": 7.926,
          "vote_count": 1338,
          "origin_country": [
            "US"
          ]
        },
        {
          "adult": false,
          "backdrop_path": "/wfeyDJiPpjTsLzPFaJkzBtMwXZa.jpg",
          "id": 26463,
          "title": "A Boyfriend for Christmas",
          "original_language": "en",
          "original_title": "A Boyfriend for Christmas",
          "overview": "Holly Grant has learned a long time ago not to rely on Santa Claus leaving Mr. Right in her Christmas stocking. But Holly is in for a surprise when a handsome man arrives on her doorstep with a twinkle in his eye and Yuletide tree in tow.",
          "poster_path": "/nj4Dg2xsHzTpSvgwxRrs6uyHHjh.jpg",
          "media_type": "movie",
          "genre_ids": [
            10770,
            10749,
            35,
            18,
            10751
          ],
          "popularity": 7.066,
          "release_date": "2004-11-27",
          "video": false,
          "vote_average": 5.648,
          "vote_count": 54
        },
        {
          "adult": false,
          "backdrop_path": "/561MNVX34MCadXsuLTOwxc3jRGt.jpg",
          "id": 489755,
          "title": "Christmas Solo",
          "original_language": "en",
          "original_title": "Christmas Solo",
          "overview": "Two single parents stumble into the possibility of love for Christmas, only to discover that their daughters are embroiled in a nasty rivalry at school. When the rivalry gets out of control, can hope and healing lead everyone to a peaceful and merry Christmas?",
          "poster_path": "/eTi13Vuqqfc135tUkc7BBDjotq5.jpg",
          "media_type": "movie",
          "genre_ids": [
            10749,
            10770
          ],
          "popularity": 15.173,
          "release_date": "2017-11-28",
          "video": false,
          "vote_average": 6.2,
          "vote_count": 30
        }
      ]
    },
    {
      "adult": false,
      "gender": 1,
      "id": 93663,
      "known_for_department": "Acting",
      "name": "Kellie Martin",
      "original_name": "Kellie Martin",
      "popularity": 9.948,
      "profile_path": "/l2SMcBisNoQjpSTq41VI8PoUSj2.jpg",
      "known_for": [
        {
          "adult": false,
          "backdrop_path": "/Sb2cLe2xW5OATkZZJBbGrB6qjl.jpg",
          "id": 15789,
          "title": "A Goofy Movie",
          "original_language": "en",
          "original_title": "A Goofy Movie",
          "overview": "An endearing modern-day story about how the lovable Goof bonds with his teenage son Max on a hilarious cross-country road trip. En route to the ol' fishing hole, they find themselves up to their floppy ears in misadventure!",
          "poster_path": "/bycmMhO3iIoEDzP768sUjq2RV4T.jpg",
          "media_type": "movie",
          "genre_ids": [
            10749,
            16,
            10751,
            35,
            12
          ],
          "popularity": 28.456,
          "release_date": "1995-04-07",
          "video": false,
          "vote_average": 6.987,
          "vote_count": 1623
        },
        {
          "adult": false,
          "backdrop_path": "/b1t0mS2MAqnMdh5opqi94rlDEjn.jpg",
          "id": 4588,
          "name": "ER",
          "original_language": "en",
          "original_name": "ER",
          "overview": "ER explores the inner workings of an urban teaching hospital and the critical issues faced by the dedicated physicians and staff of its overburdened emergency room.",
          "poster_path": "/rAxd8H0zGH61RWMPVZiR9zT4Nqk.jpg",
          "media_type": "tv",
          "genre_ids": [
            18
          ],
          "popularity": 404.734,
          "first_air_date": "1994-09-19",
          "vote_average": 7.832,
          "vote_count": 732,
          "origin_country": [
            "US"
          ]
        },
        {
          "adult": false,
          "backdrop_path": "/tnGkk8SH68n6DbcFg3J4oVKA5Ml.jpg",
          "id": 418,
          "name": "A Pup Named Scooby-Doo",
          "original_language": "en",
          "original_name": "A Pup Named Scooby-Doo",
          "overview": "The world's favorite chicken-hearted canine, as a puppy? That's right! And the old gang is back with him. Shaggy, Daphne, Velma, and Freddy are all here as gangly kids — goofing off, solving kid-size mysteries, and having run-ins with ghouls, ghosts, and goblins.",
          "poster_path": "/h7Ejy5N9vsaLdwDt6Mz5sWgff0U.jpg",
          "media_type": "tv",
          "genre_ids": [
            16,
            9648,
            35,
            10751,
            10762
          ],
          "popularity": 117.035,
          "first_air_date": "1988-09-10",
          "vote_average": 7.6,
          "vote_count": 258,
          "origin_country": [
            "US"
          ]
        }
      ]
    },
    {
      "adult": false,
      "gender": 1,
      "id": 17442,
      "known_for_department": "Acting",
      "name": "Kelli Garner",
      "original_name": "Kelli Garner",
      "popularity": 9.929,
      "profile_path": "/6EDL2MXZigqpjUWmRclMfqIdIXp.jpg",
      "known_for": [
        {
          "adult": false,
          "backdrop_path": "/3ViifQeQyPI4Mq9PpLYDjVMAyyH.jpg",
          "id": 149509,
          "title": "Horns",
          "original_language": "en",
          "original_title": "Horns",
          "overview": "In the aftermath of his girlfriend's mysterious death, a young man awakens to strange horns sprouting from his temples.",
          "poster_path": "/tjTy6W05mPXXw87IqpjeGNhIcM4.jpg",
          "media_type": "movie",
          "genre_ids": [
            18,
            14,
            53
          ],
          "popularity": 15.265,
          "release_date": "2013-09-06",
          "video": false,
          "vote_average": 6.3,
          "vote_count": 2176
        },
        {
          "adult": false,
          "backdrop_path": "/wNBLjvDpvTS3wyOZCecf3Jas7la.jpg",
          "id": 2567,
          "title": "The Aviator",
          "original_language": "en",
          "original_title": "The Aviator",
          "overview": "A biopic depicting the life of filmmaker and aviation pioneer Howard Hughes from 1927 to 1947, during which time he became a successful film producer and an aviation magnate, while simultaneously growing more unstable due to severe obsessive-compulsive disorder.",
          "poster_path": "/lx4kWcZc3o9PaNxlQpEJZM17XUI.jpg",
          "media_type": "movie",
          "genre_ids": [
            18
          ],
          "popularity": 27.873,
          "release_date": "2004-12-17",
          "video": false,
          "vote_average": 7.2,
          "vote_count": 4969
        },
        {
          "adult": false,
          "backdrop_path": "/pQdPwpP9r9ndDoNpctvZxq20brK.jpg",
          "id": 6615,
          "title": "Lars and the Real Girl",
          "original_language": "en",
          "original_title": "Lars and the Real Girl",
          "overview": "Extremely shy Lars finds it impossible to make friends or socialize. His brother and sister-in-law worry about him, so when he announces that he has a girlfriend he met on the Internet, they are overjoyed. But Lars' new lady is a life-size plastic woman. On the advice of a doctor, his family and the rest of the community go along with his delusion.",
          "poster_path": "/nkAt4a7KIPc7Fi1BhxNHhYYbe2b.jpg",
          "media_type": "movie",
          "genre_ids": [
            35,
            18,
            10749
          ],
          "popularity": 15.263,
          "release_date": "2007-10-12",
          "video": false,
          "vote_average": 7.161,
          "vote_count": 1654
        }
      ]
    },
    {
      "adult": false,
      "gender": 1,
      "id": 206637,
      "known_for_department": "Acting",
      "name": "Kelli Giddish",
      "original_name": "Kelli Giddish",
      "popularity": 11.739,
      "profile_path": "/3zcqEyAguRhYofePyJehWm19uUX.jpg",
      "known_for": [
        {
          "adult": false,
          "backdrop_path": "/9xxLWtnFxkpJ2h1uthpvCRK6vta.jpg",
          "id": 2734,
          "name": "Law \u0026 Order: Special Victims Unit",
          "original_language": "en",
          "original_name": "Law \u0026 Order: Special Victims Unit",
          "overview": "In the criminal justice system, sexually-based offenses are considered especially heinous. In New York City, the dedicated detectives who investigate these vicious felonies are members of an elite squad known as the Special Victims Unit. These are their stories.",
          "poster_path": "/ywBt4WKADdMVgxTR1rS2uFwMYTH.jpg",
          "media_type": "tv",
          "genre_ids": [
            80,
            18,
            9648
          ],
          "popularity": 3562.52,
          "first_air_date": "1999-09-20",
          "vote_average": 7.961,
          "vote_count": 3457,
          "origin_country": [
            "US"
          ]
        },
        {
          "adult": false,
          "backdrop_path": "/7q0GtTNA9j7vTZsTwuue0A3PYGt.jpg",
          "id": 32800,
          "name": "Chase",
          "original_language": "en",
          "original_name": "Chase",
          "overview": "Chase is an American police procedural drama television series created by Jennifer Johnson for the NBC network. The series follows a U.S. Marshals fugitive-apprehension team, based out of Houston, Texas. Jerry Bruckheimer and Johnson serve as executive producers for the one-hour drama. The series originally aired on Mondays at 10:00 pm ET/9:00 pm CT and premiered on September 20, 2010. After the mid-season break, Chase returned on Wednesdays at 9:00 pm ET/8:00 pm CT On October 19, 2010, the network ordered a full season consisting of 22 episodes, but this order was cut to 18 in December. On February 3, 2011, the show was put on \"a hiatus\" with no plan regarding the remaining episodes. On April 6, 2011, NBC announced the remaining five episodes would be broadcast on Saturday nights beginning on April 23, 2011. Later the show was replaced by Harry's Law.",
          "poster_path": "/sayLpKaFnTrgmIvIMmItGbyCXb4.jpg",
          "media_type": "tv",
          "genre_ids": [
            18,
            10759,
            80
          ],
          "popularity": 107.4,
          "first_air_date": "2010-09-20",
          "vote_average": 6.857,
          "vote_count": 28,
          "origin_country": [
            "US"
          ]
        },
        {
          "adult": false,
          "backdrop_path": "/yHDWux9iFWSDGAOl5brAs7dDDvB.jpg",
          "id": 122930,
          "title": "Breathless",
          "original_language": "en",
          "original_title": "Breathless",
          "overview": "Lorna is a strong-willed Texas woman who’s had enough of her untrustworthy husband, Dale’s, criminal acts and lack of husbandry. Fed up, she enlists the help of her old friend, Tiny, to help her figure out what to do with Dale after his latest double-cross involving the theft of $100,000 from a bank.",
          "poster_path": "/dL8n5BYEw19orrAAuKnzbNbmH7u.jpg",
          "media_type": "movie",
          "genre_ids": [
            35,
            53,
            9648,
            80
          ],
          "popularity": 8.183,
          "release_date": "2012-01-04",
          "video": false,
          "vote_average": 5.8,
          "vote_count": 44
        }
      ]
    },
    {
      "adult": false,
      "gender": 1,
      "id": 1254396,
      "known_for_department": "Acting",
      "name": "Kelli Berglund",
      "original_name": "Kelli Berglund",
      "popularity": 4.914,
      "profile_path": "/2Xz520XU0NPz3ZyNIpIIOeeDdaE.jpg",
      "known_for": [
        {
          "adult": false,
          "backdrop_path": "/vt5UhqjyWYbmJdZhrQsWpRCqCra.jpg",
          "id": 286987,
          "title": "How to Build a Better Boy",
          "original_language": "en",
          "original_title": "How to Build a Better Boy",
          "overview": "After inadvertently inputting the qualities of the ideal boyfriend into a high-tech government computer, two social outcasts named Mae and Gabby must contend with Albert, a cybernetic sweetheart with only objective: to treat Mae to the perfect highschool romance.",
          "poster_path": "/ivo09vYN76w3epqAv9jS9BEXi5N.jpg",
          "media_type": "movie",
          "genre_ids": [
            10751,
            878,
            10770
          ],
          "popularity": 15.87,
          "release_date": "2014-11-18",
          "video": false,
          "vote_average": 6.4,
          "vote_count": 377
        },
        {
          "adult": false,
          "backdrop_path": "/3RDkJ2jYYvOXpiCJLTjJyCnnmBI.jpg",
          "id": 396289,
          "title": "Raising the Bar",
          "original_language": "en",
          "original_title": "Raising the Bar",
          "overview": "16-year-old Kelly quits an elite gymnastics program and moves to Australia. To help out a new friend and show up an old rival she re-enters competitive gymnastics, she'll have to find a way to move forward while making amends with her past.",
          "poster_path": "/4PmeOpZK9Qvnsuo02TqBO1wHecR.jpg",
          "media_type": "movie",
          "genre_ids": [
            10751,
            18,
            10770
          ],
          "popularity": 13.747,
          "release_date": "2017-03-09",
          "video": false,
          "vote_average": 6.5,
          "vote_count": 164
        },
        {
          "adult": false,
          "backdrop_path": "/lET0XG0RLddqRYrAHHtmTdqQr8h.jpg",
          "id": 506951,
          "title": "Going for Gold",
          "original_language": "en",
          "original_title": "Going for Gold",
          "overview": "Seventeen year old, Emma joins a high school cheerleading team when she moves to Australia with her dad who is a former Air Force Officer.",
          "poster_path": "/opXqHtQ9qxbhOeWUSUsONvz79Je.jpg",
          "media_type": "movie",
          "genre_ids": [
            18,
            10751
          ],
          "popularity": 10.386,
          "release_date": "2018-03-08",
          "video": false,
          "vote_average": 6.8,
          "vote_count": 128
        }
      ]
    },
    {
      "adult": false,
      "gender": 1,
      "id": 1228661,
      "known_for_department": "Acting",
      "name": "Kellie Shanygne Williams",
      "original_name": "Kellie Shanygne Williams",
      "popularity": 13.003,
      "profile_path": "/iCiAPYjDj8mk35R2g5PVRbSlzvY.jpg",
      "known_for": [
        {
          "adult": false,
          "backdrop_path": "/dRv5QeDFLmokwRCVps0Dv2x3DPO.jpg",
          "id": 2685,
          "name": "Family Matters",
          "original_language": "en",
          "original_name": "Family Matters",
          "overview": "A long-running dramedy centering on the Winslow family, a middle-class African American family living in Chicago, and their pesky next-door neighbor, ultra-nerd Steve Urkel. A spin-off of Perfect Strangers.",
          "poster_path": "/lIIPV3te2mxBQBHw2rfhwkUYsHf.jpg",
          "media_type": "tv",
          "genre_ids": [
            35,
            10751
          ],
          "popularity": 1182.138,
          "first_air_date": "1989-09-22",
          "vote_average": 6.7,
          "vote_count": 245,
          "origin_country": [
            "US"
          ]
        },
        {
          "adult": false,
          "backdrop_path": null,
          "id": 14689,
          "name": "Clean House",
          "original_language": "en",
          "original_name": "Clean House",
          "overview": "Clean House is a home makeover and interior design television show, originally broadcast in 2003 which has aired 9 seasons of programs on the Style Network. Currently hosted by Tempestt Bledsoe and formerly hosted by Niecy Nash, the show brings a four-person cleanup-and-renovation crew to the homes of families to clean up clutter.\n\nIn 2010, Nash announced that she would be leaving the series, though it will continue on without her. Her final episode aired on December 1, 2010. Later that month, the Style Network confirmed that former Cosby Show cast member Tempestt Bledsoe will take over as host. Her first episode aired on January 26, 2011. As of 2013, the show has believed to have been canceled due to low ratings after Nash's departure.",
          "poster_path": "/uDWKn1VYZ3ABTpXHUS8QBxLe99C.jpg",
          "media_type": "tv",
          "genre_ids": [],
          "popularity": 156.792,
          "first_air_date": "2003-09-03",
          "vote_average": 6.714,
          "vote_count": 7,
          "origin_country": [
            "US"
          ]
        },
        {
          "adult": false,
          "backdrop_path": "/tmtYrgOPh7AmlM5F5KEM0eB6nxW.jpg",
          "id": 1045653,
          "title": "A Family Matters Christmas",
          "original_language": "en",
          "original_title": "A Family Matters Christmas",
          "overview": "Christmas is anything but ordinary when three bickering siblings from a newly blended household cannot see eye to eye. The youngest one, while completing his annual science project, accidentally calls upon the spirit of Christmas. They wake up to find themselves having switched bodies, unable to change back until they learn to spend the holidays together as a loving family.",
          "poster_path": "/gu0K9gnvKpfJI9TzsbrJwZJWj41.jpg",
          "media_type": "movie",
          "genre_ids": [
            14,
            10751,
            35
          ],
          "popularity": 1.849,
          "release_date": "2022-11-07",
          "video": false,
          "vote_average": 5.5,
          "vote_count": 1
        }
      ]
    },
    {
      "adult": false,
      "gender": 1,
      "id": 206889,
      "known_for_department": "Acting",
      "name": "Kelli Goss",
      "original_name": "Kelli Goss",
      "popularity": 2.74,
      "profile_path": "/6PYw3a1TxO4waW7AuEou3LcQIoc.jpg",
      "known_for": [
        {
          "adult": false,
          "backdrop_path": "/rIycDdkLET20EVW2LPytLNuyOp3.jpg",
          "id": 65493,
          "name": "The Ranch",
          "original_language": "en",
          "original_name": "The Ranch",
          "overview": "Being a pro athlete didn't pan out for Colt. Now he's helping his dad and brother keep the ranch afloat, and figuring out how he fits into the family.",
          "poster_path": "/lrbHBAxF9Ir83rxgeBrfmEJriLt.jpg",
          "media_type": "tv",
          "genre_ids": [
            35,
            10751
          ],
          "popularity": 86.613,
          "first_air_date": "2016-04-01",
          "vote_average": 7.558,
          "vote_count": 199,
          "origin_country": [
            "US"
          ]
        },
        {
          "adult": false,
          "backdrop_path": "/7RySzFeK3LPVMXcPtqfZnl6u4p1.jpg",
          "id": 1418,
          "name": "The Big Bang Theory",
          "original_language": "en",
          "original_name": "The Big Bang Theory",
          "overview": "Physicists Leonard and Sheldon find their nerd-centric social circle with pals Howard and Raj expanding when aspiring actress Penny moves in next door.",
          "poster_path": "/ooBGRQBdbGzBxAVfExiO8r7kloA.jpg",
          "media_type": "tv",
          "genre_ids": [
            35
          ],
          "popularity": 773.931,
          "first_air_date": "2007-09-24",
          "vote_average": 7.889,
          "vote_count": 10507,
          "origin_country": [
            "US"
          ]
        },
        {
          "adult": false,
          "backdrop_path": "/1jAYY94y5YeYl7cPMHRl4NBexAb.jpg",
          "id": 87016,
          "title": "Sexting in Suburbia",
          "original_language": "en",
          "original_title": "Sexting in Suburbia",
          "overview": "moody daughters, Rachel and Dina have a close relationship. Dina tells her everything... or so Rachel thinks. When Dina suddenly commits suicide, Rachel is devastated and confused. Her search for answers as to what happened in her daughter's final days leads her to some painful discoveries about the secrets that Dina was trying to keep and the bullying that was tearing her apart.",
          "poster_path": "/4Z6eZF62G192ONI5DLrNS8iMpfD.jpg",
          "media_type": "movie",
          "genre_ids": [
            18,
            53,
            10770
          ],
          "popularity": 7.054,
          "release_date": "2012-01-14",
          "video": false,
          "vote_average": 5.7,
          "vote_count": 39
        }
      ]
    },
    {
      "adult": false,
      "gender": 1,
      "id": 98087,
      "known_for_department": "Acting",
      "name": "Kellita Smith",
      "original_name": "Kellita Smith",
      "popularity": 6.119,
      "profile_path": "/fH1yOmV3Fn0L0aaWbOtYSp0dj9Z.jpg",
      "known_for": [
        {
          "adult": false,
          "backdrop_path": "/jCvwvSH5i9bLaql1rR21j9U9LS.jpg",
          "id": 61345,
          "name": "Z Nation",
          "original_language": "en",
          "original_name": "Z Nation",
          "overview": "Three years after the zombie virus has gutted the country, a team of everyday heroes must transport the only known survivor of the plague from New York to California, where the last functioning viral lab waits for his blood.",
          "poster_path": "/gXfeDMkEcHoYBvtkbU11g3F81b.jpg",
          "media_type": "tv",
          "genre_ids": [
            9648,
            10759,
            18
          ],
          "popularity": 282.163,
          "first_air_date": "2014-09-12",
          "vote_average": 7.199,
          "vote_count": 767,
          "origin_country": [
            "US"
          ]
        },
        {
          "adult": false,
          "backdrop_path": "/mNXnh4Ua8wMvSlAiXXzX7G3Ko5p.jpg",
          "id": 207717,
          "name": "From Scratch",
          "original_language": "en",
          "original_name": "From Scratch",
          "overview": "An artist finds romance with a chef in Italy and embarks on a life-changing journey of love, loss, resilience and hope across cultures and continents.",
          "poster_path": "/s8D32MA8NlNgixnAIxVbmt9cazX.jpg",
          "media_type": "tv",
          "genre_ids": [
            18
          ],
          "popularity": 25.574,
          "first_air_date": "2022-10-21",
          "vote_average": 7.718,
          "vote_count": 158,
          "origin_country": [
            "US"
          ]
        },
        {
          "adult": false,
          "backdrop_path": "/oi9RFxqb5Tncm7VvDnVT6sZUWyH.jpg",
          "id": 27526,
          "title": "The Crossing Guard",
          "original_language": "en",
          "original_title": "The Crossing Guard",
          "overview": "After his daughter died in a hit and run, Freddy Gale has waited six years for John Booth, the man responsible, to be released from prison. On the day of release, Gale visits Booth and announces that he will kill him in one week. Booth uses his time to try and make peace with himself and his entourage, and even finds romance. Gale, whose life is spiraling down because of his obsession towards Booth, will bring himself on the very edge of sanity. At he end of the week, both men will find themselves on a collision course with each other.",
          "poster_path": "/kogaCIIylHmWQo2gJrrdq8Br8b8.jpg",
          "media_type": "movie",
          "genre_ids": [
            18,
            53
          ],
          "popularity": 20.061,
          "release_date": "1995-11-15",
          "video": false,
          "vote_average": 6.0,
          "vote_count": 234
        }
      ]
    },
    {
      "adult": false,
      "gender": 1,
      "id": 99097,
      "known_for_department": "Acting",
      "name": "Kelli McCarty",
      "original_name": "Kelli McCarty",
      "popularity": 6.606,
      "profile_path": "/zZu04UCMZQG3zwsfhDD8wRKJkpH.jpg",
      "known_for": [
        {
          "adult": false,
          "backdrop_path": null,
          "id": 452006,
          "title": "Talk Sex",
          "original_language": "en",
          "original_title": "Talk Sex",
          "overview": "An attractive radio hot line worker becomes romantically involved with callers.",
          "poster_path": "/tJHHygwJl2YQ9oM0o9PPKup59Xe.jpg",
          "media_type": "movie",
          "genre_ids": [
            10749,
            18
          ],
          "popularity": 3.424,
          "release_date": "2001-01-01",
          "video": false,
          "vote_average": 6.0,
          "vote_count": 20
        },
        {
          "adult": false,
          "backdrop_path": null,
          "id": 61064,
          "title": "Passion's Peak",
          "original_language": "en",
          "original_title": "Passion's Peak",
          "overview": "Christina returns to the mountain town where she grew up, and opens a bed and breakfast. Thankfully her schoolgirl crush, Brad, still lives in town and is excited about helping her establish the new business. However, her ex-boyfriend James shows up with his new stripper girlfriend, in the hopes of making Christina jealous and fall back in love with him.",
          "poster_path": "/1rPzV73QryhJbcgQKtMXMOC6tQ6.jpg",
          "media_type": "movie",
          "genre_ids": [
            18,
            10749
          ],
          "popularity": 5.343,
          "release_date": "2000-12-12",
          "video": false,
          "vote_average": 4.2,
          "vote_count": 5
        },
        {
          "adult": false,
          "backdrop_path": "/k9CFQXTQ85ocSbWrTzOmbFw36Q0.jpg",
          "id": 110584,
          "title": "Dangerous Attractions",
          "original_language": "en",
          "original_title": "Dangerous Attractions",
          "overview": "A detective goes searching for a woman who has been killing men after having sex with them, only to bond with the woman and decides to protect her.",
          "poster_path": "/oUiMIn6xhfiIhZgTbVxMLZZMlUj.jpg",
          "media_type": "movie",
          "genre_ids": [
            10749
          ],
          "popularity": 6.563,
          "release_date": "2010-01-01",
          "video": false,
          "vote_average": 6.0,
          "vote_count": 4
        }
      ]
    },
    {
      "adult": false,
      "gender": 2,
      "id": 1225028,
      "known_for_department": "Production",
      "name": "Daniel Kellison",
      "original_name": "Daniel Kellison",
      "popularity": 0.6,
      "profile_path": "/jPbsDpVgBm4hCgadsZ9EYgdEEPn.jpg",
      "known_for": [
        {
          "adult": false,
          "backdrop_path": "/xCdCsHCH7VCQqaDUPD5tG6omMsB.jpg",
          "id": 1489,
          "name": "Jimmy Kimmel Live!",
          "original_language": "en",
          "original_name": "Jimmy Kimmel Live!",
          "overview": "Jimmy Kimmel Live! is an American late-night talk show, created and hosted by Jimmy Kimmel and broadcast on ABC.",
          "poster_path": "/hWLCBGQ2RFpjXyaKRMbL5bGEEDT.jpg",
          "media_type": "tv",
          "genre_ids": [
            10767,
            35
          ],
          "popularity": 893.316,
          "first_air_date": "2003-01-26",
          "vote_average": 5.554,
          "vote_count": 130,
          "origin_country": [
            "US"
          ]
        },
        {
          "adult": false,
          "backdrop_path": "/ywEyv1f59ICWHLlSVsYVZLYb79Q.jpg",
          "id": 459295,
          "title": "Sarah Silverman: A Speck of Dust",
          "original_language": "en",
          "original_title": "Sarah Silverman: A Speck of Dust",
          "overview": "In her first comedy special post-health scare, Sarah Silverman shares a mix of fun facts, sad truths and yeah-she-just-went-there moments.",
          "poster_path": "/bvTyPBdS4tiJ4Nv2zPnT9kAjSoD.jpg",
          "media_type": "movie",
          "genre_ids": [
            35
          ],
          "popularity": 8.771,
          "release_date": "2017-05-30",
          "video": false,
          "vote_average": 6.9,
          "vote_count": 98
        },
        {
          "adult": false,
          "backdrop_path": "/q8SnrVhqbB8P2vb1ok70yhpDlpL.jpg",
          "id": 5580,
          "name": "The Man Show",
          "original_language": "en",
          "original_name": "The Man Show",
          "overview": "The Man Show is an American comedy television show on Comedy Central. It was created in 1999 by its two original co-hosts, Jimmy Kimmel and Adam Carolla, and their executive producer Daniel Kellison.",
          "poster_path": "/jjBnTzDJzXnQ9PzwLHGFNp9ykMA.jpg",
          "media_type": "tv",
          "genre_ids": [
            35
          ],
          "popularity": 32.799,
          "first_air_date": "1999-06-15",
          "vote_average": 6.133,
          "vote_count": 30,
          "origin_country": [
            "US"
          ]
        }
      ]
    },
    {
      "adult": false,
      "gender": 1,
      "id": 21750,
      "known_for_department": "Acting",
      "name": "Petra Kelling",
      "original_name": "Petra Kelling",
      "popularity": 1.338,
      "profile_path": "/w1B6CJjG0YgO1Sxej8LGLEPyzh9.jpg",
      "known_for": [
        {
          "adult": false,
          "backdrop_path": "/4aciRChTrbvlVXI8DNVeG0K2qTy.jpg",
          "id": 2117,
          "title": "Sophie Scholl: The Final Days",
          "original_language": "de",
          "original_title": "Sophie Scholl – Die letzten Tage",
          "overview": "In 1943, as Hitler continues to wage war across Europe, a group of college students mount an underground resistance movement in Munich. Dedicated expressly to the downfall of the monolithic Third Reich war machine, they call themselves the White Rose. One of its few female members, Sophie Scholl is captured during a dangerous mission to distribute pamphlets on campus with her brother Hans. Unwavering in her convictions and loyalty to the White Rose, her cross-examination by the Gestapo quickly escalates into a searing test of wills as Scholl delivers a passionate call to freedom and personal responsibility.",
          "poster_path": "/84HWRlRwpOjZ4cYlmFZjDGyvB5q.jpg",
          "media_type": "movie",
          "genre_ids": [
            18,
            36
          ],
          "popularity": 14.618,
          "release_date": "2005-02-13",
          "video": false,
          "vote_average": 7.2,
          "vote_count": 391
        },
        {
          "adult": false,
          "backdrop_path": "/As0Mex8uhCGWnihqeEbbQ2xGwyo.jpg",
          "id": 79016,
          "title": "Homevideo",
          "original_language": "de",
          "original_title": "Homevideo",
          "overview": "Shy, sensitive high school outsider Jakob Moormann is miserably lacking immaterial support at home, where his strict father, uniformed cop Claas, and selfish mother are too busy breaking up to be there for him. Jakob focuses on class dream-girl Hannah, without much luck. His secret recording of himself masturbating gets into class bullies Henry and Erik's hands through the mother's thoughtlessness. The rascals blackmail Jakob and post the video on the Internet. After a raging lecture phase, dad stands up for Jakob, but his life is already wrecked more than anyone realizes.",
          "poster_path": "/4tbyRMlETn7RwobflixlZ1uz0f4.jpg",
          "media_type": "movie",
          "genre_ids": [
            18
          ],
          "popularity": 2.48,
          "release_date": "2011-08-18",
          "video": false,
          "vote_average": 6.6,
          "vote_count": 38
        },
        {
          "adult": false,
          "backdrop_path": "/mR0WeV40Djfktl8L5vouOBRdW1i.jpg",
          "id": 86760,
          "title": "Crash Point: Berlin",
          "original_language": "de",
          "original_title": "Crashpoint - 90 Minuten bis zum Absturz",
          "overview": "After a mid-air collision, an uncontrollable passenger plane with 90 souls on board speeds through the skies over Germany. The impact point for the inevitable plane crash is easily calculated: the center of Berlin. Now the race is on to prevent the catastrophe. Will the plane have to be shot down by fighter pilots?",
          "poster_path": "/kYB4n8TL1WF2zdYZ1yRQloiV3ZH.jpg",
          "media_type": "movie",
          "genre_ids": [
            18,
            53
          ],
          "popularity": 4.017,
          "release_date": "2009-08-17",
          "video": false,
          "vote_average": 6.0,
          "vote_count": 30
        }
      ]
    },
    {
      "adult": false,
      "gender": 2,
      "id": 50762,
      "known_for_department": "Acting",
      "name": "Mike Kellin",
      "original_name": "Mike Kellin",
      "popularity": 4.024,
      "profile_path": "/fe17vLfGXhbuLkyNQN7miebxWKu.jpg",
      "known_for": [
        {
          "adult": false,
          "backdrop_path": "/i09ge9T89Yfu1Q2DyUIQ9f9ALuC.jpg",
          "id": 11327,
          "title": "Midnight Express",
          "original_language": "en",
          "original_title": "Midnight Express",
          "overview": "Billy Hayes is caught attempting to smuggle drugs out of Turkey. The Turkish courts decide to make an example of him, sentencing him to more than 30 years in prison. Hayes has two opportunities for release: the appeals made by his lawyer, his family, and the American government, or the \"Midnight Express\".",
          "poster_path": "/s5Ap5xClitKwhLYQtuC89zOttsZ.jpg",
          "media_type": "movie",
          "genre_ids": [
            18,
            80
          ],
          "popularity": 28.778,
          "release_date": "1978-08-31",
          "video": false,
          "vote_average": 7.514,
          "vote_count": 1574
        },
        {
          "adult": false,
          "backdrop_path": "/92FqObwOmcJeOpAXhr0U568Gay2.jpg",
          "id": 13567,
          "title": "Sleepaway Camp",
          "original_language": "en",
          "original_title": "Sleepaway Camp",
          "overview": "Slightly disturbed and painfully shy Angela Baker is sent away to summer camp with her cousin. Not long after Angela's arrival, things start to go horribly wrong for anyone with sinister or less than honorable intentions.",
          "poster_path": "/lZ7KjSyHjP4ula5ybiXuQcDvZLg.jpg",
          "media_type": "movie",
          "genre_ids": [
            27
          ],
          "popularity": 16.941,
          "release_date": "1983-11-18",
          "video": false,
          "vote_average": 6.286,
          "vote_count": 614
        },
        {
          "adult": false,
          "backdrop_path": "/dqHOhehf6Nr4aCcGF4Sae5196EC.jpg",
          "id": 39982,
          "title": "Just Before Dawn",
          "original_language": "en",
          "original_title": "Just Before Dawn",
          "overview": "In the Oregon mountains, a pair of hunters encounter a machete-wielding killer in an abandoned church. Meanwhile, five campers arrive to examine some property one of them has inherited but are warned by the forest ranger not to venture forth. Soon after they set up camp, they begin hearing strange noises, encounter a mysterious singing girl and start disappearing one by one.",
          "poster_path": "/2OAvIfmnTy5HiOFOnMtaOxNwenZ.jpg",
          "media_type": "movie",
          "genre_ids": [
            27,
            53
          ],
          "popularity": 7.23,
          "release_date": "1981-10-14",
          "video": false,
          "vote_average": 6.0,
          "vote_count": 113
        }
      ]
    },
    {
      "adult": false,
      "gender": 1,
      "id": 12216,
      "known_for_department": "Acting",
      "name": "Kellie Waymire",
      "original_name": "Kellie Waymire",
      "popularity": 7.478,
      "profile_path": "/1A5MpY0BsmtgENVUaPOo52hFdDd.jpg",
      "known_for": [
        {
          "adult": false,
          "backdrop_path": "/31hKau6i2AqCUHubvl82f111jgo.jpg",
          "id": 825,
          "title": "Playing by Heart",
          "original_language": "en",
          "original_title": "Playing by Heart",
          "overview": "A sexy, romantic comedy about modern couples coming together in funny and unexpected ways. Paul and Hannah discover that even after 40 years of marriage, they can still learn some very surprising things about each other. Meredith is a serious theatre director who isn't looking for a relationship... but has one looking for her in the person of the funny, persistent Trent. Then there's Joan and Keenan, young people searching for love in an L.A. club scene where the rules of dating seem to change every night.",
          "poster_path": "/3neHR1oPnC0OpcYhLn0TEdSHoEp.jpg",
          "media_type": "movie",
          "genre_ids": [
            35,
            18,
            10749
          ],
          "popularity": 16.817,
          "release_date": "1998-12-30",
          "video": false,
          "vote_average": 6.669,
          "vote_count": 195
        },
        {
          "adult": false,
          "backdrop_path": "/l0qVZIpXtIo7km9u5Yqh0nKPOr5.jpg",
          "id": 1668,
          "name": "Friends",
          "original_language": "en",
          "original_name": "Friends",
          "overview": "Six young people from New York City, on their own and struggling to survive in the real world, find the companionship, comfort and support they get from each other to be the perfect antidote to the pressures of life.",
          "poster_path": "/2koX1xLkpTQM4IZebYvKysFW1Nh.jpg",
          "media_type": "tv",
          "genre_ids": [
            35
          ],
          "popularity": 1316.099,
          "first_air_date": "1994-09-22",
          "vote_average": 8.442,
          "vote_count": 7388,
          "origin_country": [
            "US"
          ]
        },
        {
          "adult": false,
          "backdrop_path": "/1wtK3GNY5pPTdnhnyaqcCJZ9R7k.jpg",
          "id": 210739,
          "title": "Maniacts",
          "original_language": "en",
          "original_title": "Maniacts",
          "overview": "Two serial killers meet and fall in love in an asylum for the criminally insane. Upon escaping their corrupt captors, they flee to the country to try and lead a happy, normal life. Unfortunately, \"normal\" turns out to be a state of mind...an elusive state of mind.",
          "poster_path": "/bMS5o0dyxWIozJBhoixNMpE3uDX.jpg",
          "media_type": "movie",
          "genre_ids": [
            27,
            53,
            35
          ],
          "popularity": 5.547,
          "release_date": "2001-12-06",
          "video": false,
          "vote_average": 6.0,
          "vote_count": 8
        }
      ]
    },
    {
      "adult": false,
      "gender": 1,
      "id": 968851,
      "known_for_department": "Acting",
      "name": "Kelli Barrett",
      "original_name": "Kelli Barrett",
      "popularity": 10.004,
      "profile_path": "/oFY6w4H6zEx1FDOXEXmCINnlcap.jpg",
      "known_for": [
        {
          "adult": false,
          "backdrop_path": "/j5aOOtsJinQtyRaqiB12TTRHdeX.jpg",
          "id": 67178,
          "name": "Marvel's The Punisher",
          "original_language": "en",
          "original_name": "Marvel's The Punisher",
          "overview": "A former Marine out to punish the criminals responsible for his family's murder finds himself ensnared in a military conspiracy.",
          "poster_path": "/y6wYElX5HaPZItVGJcYGdQO7k8g.jpg",
          "media_type": "tv",
          "genre_ids": [
            10759,
            80,
            18
          ],
          "popularity": 351.191,
          "first_air_date": "2017-11-17",
          "vote_average": 8.1,
          "vote_count": 2278,
          "origin_country": [
            "US"
          ]
        },
        {
          "adult": false,
          "backdrop_path": "/dmdfIman0PmPpFPJJJYQvPjlVyP.jpg",
          "id": 23169,
          "title": "Remember Me",
          "original_language": "en",
          "original_title": "Remember Me",
          "overview": "Still reeling from a heartbreaking family event and his parents' subsequent divorce, Tyler Hawkins discovers a fresh lease on life when he meets Ally Craig, a gregarious beauty who witnessed her mother's death. But as the couple draws closer, the fallout from their separate tragedies jeopardizes their love.",
          "poster_path": "/j7umuMiLCHvWT7wYhFKJOTFSokF.jpg",
          "media_type": "movie",
          "genre_ids": [
            18,
            10749
          ],
          "popularity": 37.529,
          "release_date": "2010-03-11",
          "video": false,
          "vote_average": 7.109,
          "vote_count": 3404
        },
        {
          "adult": false,
          "backdrop_path": "/lLKQCtN7IyPLGGWIuF9OP5O5m5Q.jpg",
          "id": 58224,
          "title": "Mr. Popper's Penguins",
          "original_language": "en",
          "original_title": "Mr. Popper's Penguins",
          "overview": "Jim Carrey stars as Tom Popper, a successful businessman who’s clueless when it comes to the really important things in life...until he inherits six “adorable” penguins, each with its own unique personality. Soon Tom’s rambunctious roommates turn his swank New York apartment into a snowy winter wonderland — and the rest of his world upside-down.",
          "poster_path": "/jGwZ1QI5DaL7mHQ2ZsMV1p8xvPS.jpg",
          "media_type": "movie",
          "genre_ids": [
            35,
            10751
          ],
          "popularity": 25.916,
          "release_date": "2011-06-17",
          "video": false,
          "vote_average": 5.934,
          "vote_count": 2742
        }
      ]
    },
    {
      "adult": false,
      "gender": 1,
      "id": 51528,
      "known_for_department": "Acting",
      "name": "Kelli Fox",
      "original_name": "Kelli Fox",
      "popularity": 1.103,
      "profile_path": "/rWbfvKrINW9EZHF7sCif7ZxiKIk.jpg",
      "known_for": [
        {
          "adult": false,
          "backdrop_path": "/7A4FJCsG26vOi9TUwFXdZMuzmOh.jpg",
          "id": 8831,
          "title": "Timecop",
          "original_language": "en",
          "original_title": "Timecop",
          "overview": "An officer for a security agency that regulates time travel, must fend for his life against a shady politician who has a tie to his past.",
          "poster_path": "/bgxP6ws8ErBiarnb4S93vv0lkf4.jpg",
          "media_type": "movie",
          "genre_ids": [
            53,
            878,
            28,
            80
          ],
          "popularity": 19.768,
          "release_date": "1994-09-15",
          "video": false,
          "vote_average": 6.0,
          "vote_count": 1068
        },
        {
          "adult": false,
          "backdrop_path": "/xkILTz8pP95x2VCX1otwszaFeOv.jpg",
          "id": 57789,
          "title": "Double, Double, Toil and Trouble",
          "original_language": "en",
          "original_title": "Double, Double, Toil and Trouble",
          "overview": "On Halloween night, two precocious little girls try to save their parents from their nasty old capitalist aunt's greedy clutches. Magic abounds and they meet mysterious new friends along the way.",
          "poster_path": "/3nMrq5z9b8pADKGop7aAFk0DUtP.jpg",
          "media_type": "movie",
          "genre_ids": [
            10751,
            10770,
            27,
            35,
            14
          ],
          "popularity": 9.253,
          "release_date": "1993-10-30",
          "video": false,
          "vote_average": 6.5,
          "vote_count": 100
        },
        {
          "adult": false,
          "backdrop_path": "/xXRsKNJHTOGrs5wfYAxkbM2RiyT.jpg",
          "id": 71712,
          "name": "The Good Doctor",
          "original_language": "en",
          "original_name": "The Good Doctor",
          "overview": "Shaun Murphy, a young surgeon with autism and savant syndrome, relocates from a quiet country life to join a prestigious hospital's surgical unit. Unable to personally connect with those around him, Shaun uses his extraordinary medical gifts to save lives and challenge the skepticism of his colleagues.",
          "poster_path": "/luhKkdD80qe62fwop6sdrXK9jUT.jpg",
          "media_type": "tv",
          "genre_ids": [
            18
          ],
          "popularity": 584.806,
          "first_air_date": "2017-09-25",
          "vote_average": 8.501,
          "vote_count": 11910,
          "origin_country": [
            "US"
          ]
        }
      ]
    },
    {
      "adult": false,
      "gender": 2,
      "id": 2375821,
      "known_for_department": "Acting",
      "name": "Etienne Kellici",
      "original_name": "Etienne Kellici",
      "popularity": 5.159,
      "profile_path": null,
      "known_for": [
        {
          "adult": false,
          "backdrop_path": "/oJ1MIABA0WF0a7MDVQnnMvBdex8.jpg",
          "id": 567609,
          "title": "Ready or Not",
          "original_language": "en",
          "original_title": "Ready or Not",
          "overview": "A bride's wedding night takes a sinister turn when her eccentric new in-laws force her to take part in a terrifying game.",
          "poster_path": "/vOl6shtL0wknjaIs6JdKCpcHvg8.jpg",
          "media_type": "movie",
          "genre_ids": [
            35,
            27,
            53
          ],
          "popularity": 43.236,
          "release_date": "2019-08-21",
          "video": false,
          "vote_average": 7.063,
          "vote_count": 3992
        },
        {
          "adult": false,
          "backdrop_path": "/7tJSulnvERJn6R9Ih2C2Uvpm8zy.jpg",
          "id": 881211,
          "title": "Snoopy Presents: For Auld Lang Syne",
          "original_language": "en",
          "original_title": "Snoopy Presents: For Auld Lang Syne",
          "overview": "After finding out her grandmother won't be visiting for Christmas, Lucy decides to cheer herself up by throwing the ultimate New Year's Eve party. Meanwhile, Charlie Brown tries to fulfill one of his resolutions before the clock strikes midnight.",
          "poster_path": "/p0ONYt2cw0vPEnZIoOHq1Ki7Ifm.jpg",
          "media_type": "movie",
          "genre_ids": [
            16,
            10751
          ],
          "popularity": 15.184,
          "release_date": "2021-12-09",
          "video": false,
          "vote_average": 7.191,
          "vote_count": 94
        },
        {
          "adult": false,
          "backdrop_path": "/67eYc8TlD7GMlmWkQjKU9kFjB9c.jpg",
          "id": 975490,
          "title": "Snoopy Presents: Lucy's School",
          "original_language": "en",
          "original_title": "Snoopy Presents: Lucy's School",
          "overview": "The Peanuts gang is nervous about going to a new school, so Lucy starts her own. She soon learns that teaching is tougher than she thought—and that change can be a good thing.",
          "poster_path": "/lJgiZrEIH3LKEwiZjWmpWDPETrT.jpg",
          "media_type": "movie",
          "genre_ids": [
            10751,
            16
          ],
          "popularity": 15.898,
          "release_date": "2022-08-11",
          "video": false,
          "vote_average": 7.4,
          "vote_count": 27
        }
      ]
    },
    {
      "adult": false,
      "gender": 1,
      "id": 83151,
      "known_for_department": "Acting",
      "name": "Kelli Maroney",
      "original_name": "Kelli Maroney",
      "popularity": 3.674,
      "profile_path": "/zGzOX9doZPIfoTw5t0zYGZH0Lj4.jpg",
      "known_for": [
        {
          "adult": false,
          "backdrop_path": "/4wLJxD1VZLyWNGcHKFo6YnGPMb5.jpg",
          "id": 18462,
          "title": "Night of the Comet",
          "original_language": "en",
          "original_title": "Night of the Comet",
          "overview": "Two girls from the Valley wake up to find that a passing comet has eradicated their world and left behind a mysterious red-dust and a pack of cannibal mutants. With the help of a friendly truck driver, the girls save the earth from a villainous \"think tank,\" karate chop their way through flesh-eating zombies, and, of course, find time to go to the mall.",
          "poster_path": "/xQIBwbwwKVjdkHurv3r82BUdNSq.jpg",
          "media_type": "movie",
          "genre_ids": [
            35,
            27,
            878
          ],
          "popularity": 12.323,
          "release_date": "1984-11-16",
          "video": false,
          "vote_average": 6.2,
          "vote_count": 336
        },
        {
          "adult": false,
          "backdrop_path": "/58MHmZ05sdhH8eXDCBdlUVACkSy.jpg",
          "id": 28941,
          "title": "Chopping Mall",
          "original_language": "en",
          "original_title": "Chopping Mall",
          "overview": "A group of teenagers that work at the mall all get together for a late night party in one of the stores. When the mall goes on lock down before they can get out, the robot security system activates after a malfunction and goes on a killing spree. One by one the three bots try to rid the mall of the “intruders.” The only weapons the kids can use are the supplies in other stores, or if they can make it till morning when the mall opens back up.",
          "poster_path": "/lQEbDGEOl4EPCbSzYLgs2T8t7Pu.jpg",
          "media_type": "movie",
          "genre_ids": [
            27,
            878
          ],
          "popularity": 24.911,
          "release_date": "1986-03-21",
          "video": false,
          "vote_average": 5.837,
          "vote_count": 322
        },
        {
          "adult": false,
          "backdrop_path": "/uTz92k0CfZpn1p3xRmPbgt7MQTz.jpg",
          "id": 13342,
          "title": "Fast Times at Ridgemont High",
          "original_language": "en",
          "original_title": "Fast Times at Ridgemont High",
          "overview": "Based on the real-life adventures chronicled by Cameron Crowe, Fast Times follows a group of high school students growing up in Southern California. Stacy Hamilton and Mark Ratner are looking for a love interest, and are helped along by their older classmates, Linda Barrett and Mike Damone, respectively. At the center of the film is Jeff Spicoli, a perpetually stoned surfer who faces-off with the resolute Mr. Hand—a man convinced that everyone is on dope.",
          "poster_path": "/s1DA8H7qwoOcAEhow2rCzuQtpuO.jpg",
          "media_type": "movie",
          "genre_ids": [
            35
          ],
          "popularity": 31.29,
          "release_date": "1982-08-13",
          "video": false,
          "vote_average": 6.801,
          "vote_count": 1123
        }
      ]
    },
    {
      "adult": false,
      "gender": 1,
      "id": 1883388,
      "known_for_department": "Acting",
      "name": "Kelli Ogmundson",
      "original_name": "Kelli Ogmundson",
      "popularity": 1.925,
      "profile_path": "/8HqKuIGZlS6cpeKm9LwBlYHgVea.jpg",
      "known_for": [
        {
          "adult": false,
          "backdrop_path": "/xWZsBLc6dK3lO6EBwiCpaGZdC6z.jpg",
          "id": 210694,
          "name": "Phantom Pups",
          "original_language": "en",
          "original_name": "Phantom Pups",
          "overview": "A young boy and his family move into a haunted home, where he meets three adorable ghost pups and tries to help them turn back into real dogs.",
          "poster_path": "/kqGRszJ2JyXtRTVDmGGyrwM0sJD.jpg",
          "media_type": "tv",
          "genre_ids": [
            10751
          ],
          "popularity": 20.842,
          "first_air_date": "2022-09-30",
          "vote_average": 8.309,
          "vote_count": 55,
          "origin_country": [
            "CA"
          ]
        },
        {
          "adult": false,
          "backdrop_path": "/xXRsKNJHTOGrs5wfYAxkbM2RiyT.jpg",
          "id": 71712,
          "name": "The Good Doctor",
          "original_language": "en",
          "original_name": "The Good Doctor",
          "overview": "Shaun Murphy, a young surgeon with autism and savant syndrome, relocates from a quiet country life to join a prestigious hospital's surgical unit. Unable to personally connect with those around him, Shaun uses his extraordinary medical gifts to save lives and challenge the skepticism of his colleagues.",
          "poster_path": "/luhKkdD80qe62fwop6sdrXK9jUT.jpg",
          "media_type": "tv",
          "genre_ids": [
            18
          ],
          "popularity": 584.806,
          "first_air_date": "2017-09-25",
          "vote_average": 8.501,
          "vote_count": 11910,
          "origin_country": [
            "US"
          ]
        },
        {
          "adult": false,
          "backdrop_path": "/nVRyd8hlg0ZLxBn9RaI7mUMQLnz.jpg",
          "id": 1622,
          "name": "Supernatural",
          "original_language": "en",
          "original_name": "Supernatural",
          "overview": "When they were boys, Sam and Dean Winchester lost their mother to a mysterious and demonic supernatural force. Subsequently, their father raised them to be soldiers. He taught them about the paranormal evil that lives in the dark corners and on the back roads of America ... and he taught them how to kill it. Now, the Winchester brothers crisscross the country in their '67 Chevy Impala, battling every kind of supernatural threat they encounter along the way. ",
          "poster_path": "/KoYWXbnYuS3b0GyQPkbuexlVK9.jpg",
          "media_type": "tv",
          "genre_ids": [
            18,
            9648,
            10765
          ],
          "popularity": 3521.753,
          "first_air_date": "2005-09-13",
          "vote_average": 8.302,
          "vote_count": 7021,
          "origin_country": [
            "US"
          ]
        }
      ]
    },
    {
      "adult": false,
      "gender": 1,
      "id": 58522,
      "known_for_department": "Acting",
      "name": "Kellie Overbey",
      "original_name": "Kellie Overbey",
      "popularity": 3.954,
      "profile_path": "/oRBFREIcc44VqmlLsytQh4FDQoI.jpg",
      "known_for": [
        {
          "adult": false,
          "backdrop_path": "/yych1GDUoSs4r51o1feBnOn5szq.jpg",
          "id": 6950,
          "title": "Outbreak",
          "original_language": "en",
          "original_title": "Outbreak",
          "overview": "A deadly airborne virus finds its way into the USA and starts killing off people at an epidemic rate. Col. Sam Daniels' job is to stop the virus spreading from a small town, which must be quarantined, and to prevent an over reaction by the White House.",
          "poster_path": "/dxr5NoaIALZThSYeeaJKlMGCZlY.jpg",
          "media_type": "movie",
          "genre_ids": [
            28,
            18,
            878,
            53
          ],
          "popularity": 33.04,
          "release_date": "1995-03-10",
          "video": false,
          "vote_average": 6.534,
          "vote_count": 2082
        },
        {
          "adult": false,
          "backdrop_path": "/8D4in0vUmyzjMQHcIdQ8wyEmUca.jpg",
          "id": 9684,
          "title": "Sweet and Lowdown",
          "original_language": "en",
          "original_title": "Sweet and Lowdown",
          "overview": "In the 1930s, jazz guitarist Emmet Ray idolizes Django Reinhardt, faces gangsters and falls in love with a mute woman.",
          "poster_path": "/23S5qa8j3ajYnERcYCqMLfSeOvw.jpg",
          "media_type": "movie",
          "genre_ids": [
            35,
            18,
            10402
          ],
          "popularity": 12.66,
          "release_date": "1999-12-03",
          "video": false,
          "vote_average": 6.8,
          "vote_count": 455
        },
        {
          "adult": false,
          "backdrop_path": "/mCbh1Mzcu6AlTO4aFlfnwfKsxsE.jpg",
          "id": 9045,
          "name": "The Stand",
          "original_language": "en",
          "original_name": "The Stand",
          "overview": "After a deadly plague kills most of the world’s population, the remaining survivors split into two groups - one led by a benevolent elder and the other by a maleficent being - to face each other in a final battle between good and evil.",
          "poster_path": "/o4Gb63aXRh5mMqGifYACixnxGkQ.jpg",
          "media_type": "tv",
          "genre_ids": [
            10765,
            18
          ],
          "popularity": 193.35,
          "first_air_date": "1994-05-08",
          "vote_average": 6.822,
          "vote_count": 407,
          "origin_country": [
            "US"
          ]
        }
      ]
    }
  ],
  "total_pages": 22,
  "total_results": 437
}